{
  "version": "1.0",
  "defaultProvider": "cdnjs",
  "libraries": [
    {
      "library": "popper.js@2.9.3",
      "destination": "wwwroot/css/popper.js/"
    },
    {
      "library": "lazysizes@5.3.2",
      "destination": "wwwroot/js/lazysizes/"
    },
    {
      "library": "gsap@3.9.1",
      "destination": "wwwroot/js/gsap/"
    },
    {
      "library": "dexie@3.2.1",
      "destination": "wwwroot/js/dexie/"
    },
    {
      "provider": "jsdelivr",
      "library": "@loadingio/loading.css@3.1.0",
      "destination": "wwwroot/css/loadingio/loading.css/"
    }
  ]
}